{
  "id": "brasas-critica-u1-l3",
  "paquete": "brasas",
  "habilidad": "critica",
  "objetivo": "Reconocer si algo se puede comprobar",
  "lectura": { "dosis": "frase", "texto": "¿Cómo lo sabemos?" },
  "modos": {
    "interactivo": {
      "gancho": "Desconocido pregunta: ¿podemos comprobarlo de verdad o solo lo creemos?",
      "retos": [
        {
          "tipo": "clasificar",
          "enunciado": "¿Se puede comprobar (sí) o no?",
          "datos": {
            "frases": [
              { "texto": "Cuento cuántas sillas hay.", "categoria": "sí" },
              { "texto": "Adivino qué soñó mi amigo.", "categoria": "no" },
              { "texto": "Mido cuánto mide la mesa.", "categoria": "sí" }
            ],
            "categorias": ["sí", "no"]
          }
        },
        {
          "tipo": "seleccion",
          "enunciado": "¿Cuál sí podemos comprobar?",
          "datos": { "opciones": ["la pelota es roja", "los lunes son aburridos"], "correcta": "la pelota es roja" }
        },
        {
          "tipo": "seleccion",
          "enunciado": "Para saber si llueve, ¿qué hacemos?",
          "datos": { "opciones": ["mirar por la ventana", "preguntarle a un dibujo"], "correcta": "mirar por la ventana" }
        }
      ]
    },
    "audio_narrativo": {
      "gancho_audio": "brasas/critica/u1l3/gancho.mp3",
      "retos": [
        { "tipo": "respuesta_voz", "enunciado": "Di cómo comprobarías si hay leche en la nevera.", "datos": { "audio": "brasas/critica/u1l3/reto.mp3", "respuesta_esperada": "abrir la nevera y mirar" } }
      ]
    },
    "manual": {
      "instruccion": "Elige algo de tu casa y compruébalo midiendo o contando con tu adulto.",
      "ficha_pdf": "brasas/critica/u1l3/ficha.pdf",
      "retos": [
        { "tipo": "manual_autoconfirmado", "enunciado": "Comprueba algo contando o midiendo y marca cuando termines.", "datos": { "confirmacion": "adulto" } }
      ]
    }
  },
  "personaje": "desconocido",
  "recompensa": "medalla_comprobar"
}
